README.md
setup.py
pdf4me/__init__.py
pdf4me.egg-info/PKG-INFO
pdf4me.egg-info/SOURCES.txt
pdf4me.egg-info/dependency_links.txt
pdf4me.egg-info/requires.txt
pdf4me.egg-info/top_level.txt
pdf4me/client/__init__.py
pdf4me/client/barcode_client.py
pdf4me/client/convert_client.py
pdf4me/client/doc_generation_client.py
pdf4me/client/document_client.py
pdf4me/client/extract_client.py
pdf4me/client/image_client.py
pdf4me/client/job_client.py
pdf4me/client/management_client.py
pdf4me/client/merge_client.py
pdf4me/client/optimize_client.py
pdf4me/client/pdf4me_client.py
pdf4me/client/pdfA_client.py
pdf4me/client/split_client.py
pdf4me/client/stamp_client.py
pdf4me/client/swiss_qr_client.py
pdf4me/client/user_client.py
pdf4me/helper/__init__.py
pdf4me/helper/custom_http.py
pdf4me/helper/file_reader.py
pdf4me/helper/json_converter.py
pdf4me/helper/pdf4me_exceptions.py
pdf4me/helper/response_checker.py
pdf4me/helper/token_generator.py
pdf4me/model/__init__.py
pdf4me/model/action_flow.py
pdf4me/model/add_barcode.py
pdf4me/model/add_barcode_action.py
pdf4me/model/add_barcode_res.py
pdf4me/model/api_call_detail.py
pdf4me/model/application_token.py
pdf4me/model/applications.py
pdf4me/model/archive_config.py
pdf4me/model/archive_job_req.py
pdf4me/model/archive_job_res.py
pdf4me/model/barcode_color.py
pdf4me/model/billing_data.py
pdf4me/model/check_availability_res.py
pdf4me/model/color.py
pdf4me/model/convert_from_pdf.py
pdf4me/model/convert_from_pdf_action.py
pdf4me/model/convert_from_pdf_res.py
pdf4me/model/convert_to_pdf.py
pdf4me/model/convert_to_pdf_action.py
pdf4me/model/convert_to_pdf_res.py
pdf4me/model/create_images.py
pdf4me/model/create_images_res.py
pdf4me/model/create_mailing.py
pdf4me/model/create_mailing_res.py
pdf4me/model/create_pdf_a.py
pdf4me/model/create_pdf_a_res.py
pdf4me/model/custom_cms_config.py
pdf4me/model/customer_bo.py
pdf4me/model/delete_job_flow_plan_res.py
pdf4me/model/delete_job_flow_res.py
pdf4me/model/doc_action.py
pdf4me/model/doc_gen_document.py
pdf4me/model/doc_log.py
pdf4me/model/doc_metadata.py
pdf4me/model/doc_template.py
pdf4me/model/document.py
pdf4me/model/drop_document_req.py
