Metadata-Version: 2.1
Name: pdf4me
Version: 0.8.22
Summary: Provides expert functionality to convert, optimize, merge, split, ocr, print documents & PDFs.
Home-page: https://portal.pdf4me.com/
Author: Pdf4me
Author-email: support-dev@pdf4me.com
License: UNKNOWN
Project-URL: Bug Reports, https://github.com/pdf4me/pdf4me-clientapi-python/issues
Project-URL: Source, https://github.com/pdf4me/pdf4me-clientapi-python
Keywords: pdf convert extract thumbnails merge optimize compress split stamp ocr archive
Platform: UNKNOWN
Classifier: Development Status :: 4 - Beta
Classifier: Intended Audience :: Developers
Classifier: Topic :: Software Development
Classifier: Topic :: Other/Nonlisted Topic
Classifier: License :: OSI Approved :: MIT License
Classifier: Programming Language :: Python :: 2.7
Classifier: Programming Language :: Python :: 3.6
Requires-Python: >=2.7, <4
